dinosub/__init__.py
dinosub/main.py
dinosub-1.2.1.dist-info/METADATA
dinosub-1.2.1.dist-info/WHEEL
dinosub-1.2.1.dist-info/entry_points.txt
dinosub-1.2.1.dist-info/top_level.txt
dinosub-1.2.1.dist-info/RECORD
